__init__.py
dbcache/__init__.py
dbcache/dbcache.py
usss_dbcache-0.1.1.dist-info/licenses/LICENSE
usss_dbcache-0.1.1.dist-info/METADATA
usss_dbcache-0.1.1.dist-info/WHEEL
usss_dbcache-0.1.1.dist-info/top_level.txt
usss_dbcache-0.1.1.dist-info/RECORD
