Metadata-Version: 2.4
Name: usss-dbcache
Version: 0.1.1
Summary: Cache Manger: cache parquet compressed database table as longblob in database cache table 
Author-email: Julian Briggs <julian.briggs@sheffield.ac.uk>
License-Expression: MIT
Project-URL: Homepage, https://github.com/pypa/usss-dbcache
Project-URL: Issues, https://github.com/pypa/usss-dbcache/issues
Classifier: Programming Language :: Python :: 3
Classifier: Operating System :: OS Independent
Requires-Python: >=3.11
License-File: LICENSE
Requires-Dist: configargparse
Requires-Dist: fastparquet
Requires-Dist: pandas
Requires-Dist: pymysql
Requires-Dist: python-dotenv
Requires-Dist: pyyaml
Requires-Dist: sqlalchemy
Requires-Dist: snappy
Provides-Extra: dev
Requires-Dist: black; extra == "dev"
Requires-Dist: build; extra == "dev"
Requires-Dist: mypy; extra == "dev"
Requires-Dist: pandas-stubs; extra == "dev"
Requires-Dist: pylint-pytest; extra == "dev"
Requires-Dist: pytest; extra == "dev"
Requires-Dist: pytest-cov; extra == "dev"
Requires-Dist: pytest-mock; extra == "dev"
Requires-Dist: radon; extra == "dev"
Requires-Dist: twine; extra == "dev"
Requires-Dist: types-pymysql; extra == "dev"
Requires-Dist: types-pyyaml; extra == "dev"
Dynamic: license-file
